tenant_schemas_celery/__init__.py
tenant_schemas_celery/app.py
tenant_schemas_celery/app_test.py
tenant_schemas_celery/cache.py
tenant_schemas_celery/cache_test.py
tenant_schemas_celery/compat.py
tenant_schemas_celery/conftest.py
tenant_schemas_celery/db_scheduler.py
tenant_schemas_celery/db_scheduler_test.py
tenant_schemas_celery/integration_test.py
tenant_schemas_celery/registry.py
tenant_schemas_celery/registry_test.py
tenant_schemas_celery/scheduler.py
tenant_schemas_celery/task.py
tenant_schemas_celery/task_test.py
tenant_schemas_celery/test_app.py
tenant_schemas_celery/test_scheduler.py
tenant_schemas_celery/test_tasks.py
tenant_schemas_celery/test_utils.py
tenant_schemas_celery-4.0.3.dist-info/licenses/LICENSE
tenant_schemas_celery-4.0.3.dist-info/METADATA
tenant_schemas_celery-4.0.3.dist-info/WHEEL
tenant_schemas_celery-4.0.3.dist-info/top_level.txt
tenant_schemas_celery-4.0.3.dist-info/RECORD
