Metadata-Version: 2.4
Name: tenant-schemas-celery
Version: 4.0.3
Summary: Celery integration for django-tenant-schemas and django-tenants
Home-page: https://github.com/maciej-gol/tenant-schemas-celery
Author: Maciej Gol
Author-email: 1kroolik1@gmail.com
License: MIT
Classifier: License :: OSI Approved :: MIT License
Classifier: Framework :: Django
Classifier: Programming Language :: Python
Requires-Python: >=3.9
License-File: LICENSE
Requires-Dist: celery>=5
Dynamic: author
Dynamic: author-email
Dynamic: classifier
Dynamic: description
Dynamic: description-content-type
Dynamic: home-page
Dynamic: license
Dynamic: license-file
Dynamic: requires-dist
Dynamic: requires-python
Dynamic: summary
